{
	"name": "pl_orchestrate",
	"properties": {
		"activities": [
			{
				"name": "Execute orders ingest",
				"type": "ExecutePipeline",
				"dependsOn": [],
				"policy": {
					"secureInput": false
				},
				"userProperties": [],
				"typeProperties": {
					"pipeline": {
						"referenceName": "pl_ingest_orders",
						"type": "PipelineReference"
					},
					"waitOnCompletion": true
				}
			},
			{
				"name": "Execute order_items ingest",
				"type": "ExecutePipeline",
				"dependsOn": [
					{
						"activity": "Execute orders ingest",
						"dependencyConditions": [
							"Succeeded"
						]
					}
				],
				"policy": {
					"secureInput": false
				},
				"userProperties": [],
				"typeProperties": {
					"pipeline": {
						"referenceName": "pl_ingest_order_items",
						"type": "PipelineReference"
					},
					"waitOnCompletion": true
				}
			},
			{
				"name": "Execute process Pipeline",
				"type": "ExecutePipeline",
				"dependsOn": [
					{
						"activity": "Execute order_items ingest",
						"dependencyConditions": [
							"Succeeded"
						]
					}
				],
				"policy": {
					"secureInput": false
				},
				"userProperties": [],
				"typeProperties": {
					"pipeline": {
						"referenceName": "pl_process",
						"type": "PipelineReference"
					},
					"waitOnCompletion": true
				}
			},
			{
				"name": "Execute reporting Pipeline",
				"type": "ExecutePipeline",
				"dependsOn": [
					{
						"activity": "Execute process Pipeline",
						"dependencyConditions": [
							"Succeeded"
						]
					}
				],
				"policy": {
					"secureInput": false
				},
				"userProperties": [],
				"typeProperties": {
					"pipeline": {
						"referenceName": "pl_reporting",
						"type": "PipelineReference"
					},
					"waitOnCompletion": true
				}
			}
		],
		"annotations": []
	}
}